techharper/__init__.py
techharper/github_service.py
techharper/models/__init__.py
techharper/models/notification.py
techharper/models/release.py
techharper-0.1.1.dist-info/LICENSE
techharper-0.1.1.dist-info/METADATA
techharper-0.1.1.dist-info/WHEEL
techharper-0.1.1.dist-info/top_level.txt
techharper-0.1.1.dist-info/RECORD
