Metadata-Version: 2.1
Name: techharper
Version: 0.1.1
Summary: Tool to fetch the latest updates for technologies
Home-page: https://github.com/BoredTweak/techharper
Author: Alex Elia
Author-email: alex.elia42+pip@gmail.com
License: GPL-3
Platform: UNKNOWN
Classifier: Programming Language :: Python :: 3
Requires-Python: >=3.7
License-File: LICENSE
Requires-Dist: requests (==2.25.1)
